ncrvi/__init__.py
ncrvi/command.py
ncrvi/ncrvi.py
ncrvi/test_ncrvi.py
ncrvi-2025.8.9.0.dist-info/METADATA
ncrvi-2025.8.9.0.dist-info/WHEEL
ncrvi-2025.8.9.0.dist-info/entry_points.txt
ncrvi-2025.8.9.0.dist-info/top_level.txt
ncrvi-2025.8.9.0.dist-info/RECORD
