Metadata-Version: 2.4
Name: ncrvi
Version: 2025.8.9.0
Summary: Check rudimentary information
Author-email: Ann T Ropea <bedhanger@gmx.de>
License-Expression: MIT
Project-URL: Homepage, https://gitlab.com/bedhanger/mwe/-/tree/master/python/ncrvi
Requires-Dist: pytest
